stork/__init__.py
stork/_version.py
stork/api_error.py
stork/cli.py
stork/cli_commands.py
stork/configure.py
stork/create_job_cluster.py
stork/file_name.py
stork/update_databricks_library.py
stork-3.2.1.data/data/LICENSE.txt
stork-3.2.1.dist-info/LICENSE.txt
stork-3.2.1.dist-info/METADATA
stork-3.2.1.dist-info/WHEEL
stork-3.2.1.dist-info/entry_points.txt
stork-3.2.1.dist-info/top_level.txt
stork-3.2.1.dist-info/RECORD
